pyfftlog/__init__.py
pyfftlog/pyfftlog.py
pyfftlog/version.py
pyfftlog-0.2.1.dist-info/LICENSE
pyfftlog-0.2.1.dist-info/METADATA
pyfftlog-0.2.1.dist-info/WHEEL
pyfftlog-0.2.1.dist-info/top_level.txt
pyfftlog-0.2.1.dist-info/RECORD
