Metadata-Version: 2.1
Name: pyfftlog
Version: 0.2.1
Summary: Logarithmic Fast Fourier Transform
Author-email: The emsig community <info@emsig.xyz>
License: CC0 1.0 Universal
Project-URL: Homepage, https://pyfftlog.rtfd.io
Project-URL: Documentation, https://pyfftlog.rtfd.io
Project-URL: Repository, https://github.com/emsig/pyfftlog
Classifier: Development Status :: 5 - Production/Stable
Classifier: License :: CC0 1.0 Universal (CC0 1.0) Public Domain Dedication
Classifier: Programming Language :: Python
Requires-Python: >=3.10
License-File: LICENSE
Requires-Dist: numpy
Requires-Dist: scipy >=1.10
Provides-Extra: all
Requires-Dist: pyfftlog[docs] ; extra == 'all'
Requires-Dist: pyfftlog[tests] ; extra == 'all'
Provides-Extra: build
Requires-Dist: setuptools-scm >=8 ; extra == 'build'
Requires-Dist: setuptools >=64 ; extra == 'build'
Provides-Extra: docs
Requires-Dist: ipympl ; extra == 'docs'
Requires-Dist: sphinx ; extra == 'docs'
Requires-Dist: empymod ; extra == 'docs'
Requires-Dist: numpydoc ; extra == 'docs'
Requires-Dist: ipykernel ; extra == 'docs'
Requires-Dist: matplotlib ; extra == 'docs'
Requires-Dist: pickleshare ; extra == 'docs'
Requires-Dist: sphinx-gallery ; extra == 'docs'
Requires-Dist: sphinx-rtd-theme ; extra == 'docs'
Provides-Extra: tests
Requires-Dist: flake8 ; extra == 'tests'
Requires-Dist: pytest ; extra == 'tests'
Requires-Dist: coveralls ; extra == 'tests'
Requires-Dist: pytest-cov ; extra == 'tests'
Requires-Dist: flake8-pyproject ; extra == 'tests'
